tukuy/__init__.py
tukuy/base.py
tukuy/exceptions.py
tukuy/types.py
tukuy/core/__init__.py
tukuy/core/introspection.py
tukuy/core/registration.py
tukuy/core/unified.py
tukuy/plugins/__init__.py
tukuy/plugins/base.py
tukuy/plugins/example_decorator.py
tukuy/plugins/helper.py
tukuy/plugins/date/__init__.py
tukuy/plugins/example/__init__.py
tukuy/plugins/html/__init__.py
tukuy/plugins/json/__init__.py
tukuy/plugins/numerical/__init__.py
tukuy/plugins/text/__init__.py
tukuy/plugins/validation/__init__.py
tukuy/transformers/__init__.py
tukuy/transformers/date.py
tukuy/transformers/html.py
tukuy/transformers/json.py
tukuy/transformers/numerical.py
tukuy/transformers/text.py
tukuy/transformers/validation.py
tukuy-0.0.6.dist-info/METADATA
tukuy-0.0.6.dist-info/WHEEL
tukuy-0.0.6.dist-info/top_level.txt
tukuy-0.0.6.dist-info/RECORD
