Metadata-Version: 2.4
Name: tukuy
Version: 0.0.6
Summary: A flexible data transformation library with a plugin system
Home-page: https://github.com/jhd3197/tukuy
Author: Juan Denis
Author-email: juan@vene.co
Classifier: Programming Language :: Python :: 3
Classifier: License :: OSI Approved :: MIT License
Classifier: Operating System :: OS Independent
Requires-Python: >=3.7
Requires-Dist: beautifulsoup4>=4.9.0
Requires-Dist: python-slugify>=4.0.0
Requires-Dist: html5lib>=1.1
Dynamic: author
Dynamic: author-email
Dynamic: classifier
Dynamic: description
Dynamic: description-content-type
Dynamic: home-page
Dynamic: requires-dist
Dynamic: requires-python
Dynamic: summary
